{
    "server": {
        "env": {
            "SERVER_ID": "SquadTraining1",
            "SERVER_NAME": "training1",
            "IP_ADDRESS": "142.44.143.136",
            "PORT": "7789",
            "QUERY_PORT": "",
            "PARAMETERS": "-log",
            "MAX_PLAYERS": "80",
            "FIXEDTICKRATE": "15",
            "RANDOM": "NONE",
            "CPU_AFFINITY": "FF",
            "STEAM_BASE_PATH": "D:\\steam\\",
            "STEAM_WORKSHOP_PATH": "steamapps\\workshop\\content\\393380\\",
            "STORE_PATH": "D:\\store\\squad\\",
            "SCRIPTS_REL_PATH": "",
            "SQUAD_CONFIG_PATH": "D:\\config",
            "SQUAD_BASE_PATH": "D:\\gameservers\\squad\\training1"
            }
        }
}

